[
  {
    "name": "Knovíz",
    "lat": "50.2126",
    "lon": "14.1369"
  },
  {
    "name": "Kněžmost",
    "lat": "50.4892",
    "lon": "15.0383"
  },
  {
    "name": "Kněžice",
    "lat": "49.2704",
    "lon": "15.6727"
  },
  {
    "name": "Kněžičky",
    "lat": "50.1741",
    "lon": "15.3449"
  },
  {
    "name": "Kněževes",
    "lat": "49.4565",
    "lon": "15.9808"
  },
  {
    "name": "Kněževes",
    "lat": "49.4565",
    "lon": "15.9808"
  },
  {
    "name": "Knyk",
    "lat": "49.6469",
    "lon": "15.5786"
  },
  {
    "name": "Kněžice",
    "lat": "49.2704",
    "lon": "15.6727"
  },
  {
    "name": "Kněžnice",
    "lat": "50.4923",
    "lon": "15.3236"
  },
  {
    "name": "Kněževes",
    "lat": "49.4565",
    "lon": "15.9808"
  },
  {
    "name": "Knínice",
    "lat": "49.5397",
    "lon": "16.6950"
  },
  {
    "name": "Kněždub",
    "lat": "48.8867",
    "lon": "17.3955"
  },
  {
    "name": "Kněžice",
    "lat": "49.2704",
    "lon": "15.6727"
  },
  {
    "name": "Knínice",
    "lat": "49.5397",
    "lon": "16.6950"
  },
  {
    "name": "Kněžpole",
    "lat": "49.0985",
    "lon": "17.5167"
  },
  {
    "name": "Kněževes",
    "lat": "49.4565",
    "lon": "15.9808"
  }
]