[
  {
    "name": "Kvílice",
    "lat": "50.2581",
    "lon": "14.0023"
  },
  {
    "name": "Květnice",
    "lat": "50.0571",
    "lon": "14.6839"
  },
  {
    "name": "Kvítkovice",
    "lat": "48.9576",
    "lon": "14.3308"
  },
  {
    "name": "Květov",
    "lat": "49.4254",
    "lon": "14.2758"
  },
  {
    "name": "Kvilda",
    "lat": "49.0192",
    "lon": "13.5793"
  },
  {
    "name": "Kváskovice",
    "lat": "49.1884",
    "lon": "14.0037"
  },
  {
    "name": "Kvášňovice",
    "lat": "49.4130",
    "lon": "13.6420"
  },
  {
    "name": "Kvíčovice",
    "lat": "49.5900",
    "lon": "13.0730"
  },
  {
    "name": "Kvítkov",
    "lat": "50.6549",
    "lon": "14.4867"
  },
  {
    "name": "Květinov",
    "lat": "49.5646",
    "lon": "15.5073"
  },
  {
    "name": "Kvasiny",
    "lat": "50.2126",
    "lon": "16.2634"
  },
  {
    "name": "Květná",
    "lat": "49.7362",
    "lon": "16.3462"
  },
  {
    "name": "Kvasice",
    "lat": "49.2422",
    "lon": "17.4701"
  }
]