[
  {
    "name": "Pěčice",
    "lat": 50.3494,
    "lon": 15.0044
  },
  {
    "name": "Pětikozly",
    "lat": 50.4114,
    "lon": 14.8118
  },
  {
    "name": "Pětihosty",
    "lat": 49.8864,
    "lon": 14.7054
  },
  {
    "name": "Pěčnov",
    "lat": 49.0531,
    "lon": 13.942
  },
  {
    "name": "Pětipsy",
    "lat": 50.3208,
    "lon": 13.3498
  },
  {
    "name": "Pěčín",
    "lat": 50.1538,
    "lon": 16.4247
  },
  {
    "name": "Pěnčín (Liberec)",
    "lat": 50.5949,
    "lon": 15.0761
  },
  {
    "name": "Pěnčín (Jablonec nad Nisou)",
    "lat": 50.6877,
    "lon": 15.2359
  },
  {
    "name": "Pěnčín (Prostějov)",
    "lat": 49.5672,
    "lon": 17.0131
  }
]