[
  {
    "name": "Všeradice",
    "lat": 49.8734,
    "lon": 14.1057
  },
  {
    "name": "Všejany",
    "lat": 50.2548,
    "lon": 14.9535
  },
  {
    "name": "Všenory",
    "lat": 49.9281,
    "lon": 14.3035
  },
  {
    "name": "Vševily",
    "lat": 49.5652,
    "lon": 13.8825
  },
  {
    "name": "Všesulov",
    "lat": 50.04,
    "lon": 13.6102
  },
  {
    "name": "Všemyslice",
    "lat": 49.2162,
    "lon": 14.3573
  },
  {
    "name": "Všepadly",
    "lat": 49.4509,
    "lon": 13.1053
  },
  {
    "name": "Všekary",
    "lat": 49.6034,
    "lon": 13.0424
  },
  {
    "name": "Všenice",
    "lat": 49.8181,
    "lon": 13.5604
  },
  {
    "name": "Všelibice",
    "lat": 50.646,
    "lon": 14.9514
  },
  {
    "name": "Všeradov",
    "lat": 49.7477,
    "lon": 15.8372
  },
  {
    "name": "Všeň",
    "lat": 50.5575,
    "lon": 15.1052
  },
  {
    "name": "Všemina",
    "lat": 49.2811,
    "lon": 17.877
  },
  {
    "name": "Všechlapy (Benešov)",
    "lat": 49.779,
    "lon": 14.9142
  },
  {
    "name": "Všechlapy (Nymburk)",
    "lat": 50.2211,
    "lon": 15.0287
  },
  {
    "name": "Všechlapy (Teplice)",
    "lat": 50.6087,
    "lon": 13.7897
  },
  {
    "name": "Všechlapy (Louny)",
    "lat": 50.4583,
    "lon": 13.8371
  },
  {
    "name": "Všechlapy (Tábor)",
    "lat": 49.326,
    "lon": 14.5582
  },
  {
    "name": "Všechlapy (Strakonice)",
    "lat": 49.1328,
    "lon": 13.9591
  },
  {
    "name": "Všestudy (Mělník)",
    "lat": 50.2917,
    "lon": 14.3419
  },
  {
    "name": "Všestudy (Chomutov)",
    "lat": 50.4574,
    "lon": 13.5076
  },
  {
    "name": "Všetaty (Rakovník)",
    "lat": 50.0461,
    "lon": 13.7574
  },
  {
    "name": "Všetaty (Mělník)",
    "lat": 50.2819,
    "lon": 14.593
  },
  {
    "name": "Všestary (Hradec Králové)",
    "lat": 50.2565,
    "lon": 15.7598
  },
  {
    "name": "Všestary (Praha-východ)",
    "lat": 49.9586,
    "lon": 14.6853
  },
  {
    "name": "Všeruby (Plzeň-sever)",
    "lat": 49.8418,
    "lon": 13.2292
  },
  {
    "name": "Všeruby (Domažlice)",
    "lat": 49.3403,
    "lon": 12.9824
  },
  {
    "name": "Všehrdy (Plzeň-sever)",
    "lat": 49.9637,
    "lon": 13.5851
  },
  {
    "name": "Všehrdy (Chomutov)",
    "lat": 50.4199,
    "lon": 13.4612
  },
  {
    "name": "Všechovice (Přerov)",
    "lat": 49.4615,
    "lon": 17.7596
  },
  {
    "name": "Všechovice (Brno-venkov)",
    "lat": 49.3571,
    "lon": 16.4941
  }
]