[
  {
    "name": "Štipoklasy",
    "lat": "49.8244",
    "lon": "15.2131"
  },
  {
    "name": "Štíhlice",
    "lat": "50.0056",
    "lon": "14.7799"
  },
  {
    "name": "Štěchovice",
    "lat": "49.2555",
    "lon": "13.7655"
  },
  {
    "name": "Štětkovice",
    "lat": "49.6710",
    "lon": "14.5057"
  },
  {
    "name": "Štěpánovice",
    "lat": "49.3730",
    "lon": "16.3876"
  },
  {
    "name": "Štěchovice",
    "lat": "49.2555",
    "lon": "13.7655"
  },
  {
    "name": "Štěkeň",
    "lat": "49.2671",
    "lon": "14.0059"
  },
  {
    "name": "Štědrá",
    "lat": "50.0582",
    "lon": "13.1142"
  },
  {
    "name": "Štěnovický Borek",
    "lat": "49.6497",
    "lon": "13.4268"
  },
  {
    "name": "Štěnovice",
    "lat": "49.6705",
    "lon": "13.3996"
  },
  {
    "name": "Štichov",
    "lat": "49.5849",
    "lon": "13.0489"
  },
  {
    "name": "Štichovice",
    "lat": "49.9778",
    "lon": "13.3028"
  },
  {
    "name": "Štítov",
    "lat": "49.6015",
    "lon": "13.5678"
  },
  {
    "name": "Štětí",
    "lat": "50.4529",
    "lon": "14.3747"
  },
  {
    "name": "Štoky",
    "lat": "49.5025",
    "lon": "15.5886"
  },
  {
    "name": "Študlov",
    "lat": "49.6025",
    "lon": "16.4983"
  },
  {
    "name": "Štěchov",
    "lat": "49.4529",
    "lon": "16.5051"
  },
  {
    "name": "Štěpánovice",
    "lat": "49.3730",
    "lon": "16.3876"
  },
  {
    "name": "Štítná nad Vláří-Popov",
    "lat": "49.0698",
    "lon": "17.9752"
  },
  {
    "name": "Študlov",
    "lat": "49.6025",
    "lon": "16.4983"
  },
  {
    "name": "Štěměchy",
    "lat": "49.1933",
    "lon": "15.7147"
  },
  {
    "name": "Štěpkov",
    "lat": "49.0837",
    "lon": "15.6502"
  },
  {
    "name": "Štítary",
    "lat": "48.9351",
    "lon": "15.8443"
  },
  {
    "name": "Štěpánov nad Svratkou",
    "lat": "49.5046",
    "lon": "16.3390"
  },
  {
    "name": "Štramberk",
    "lat": "49.5912",
    "lon": "18.1170"
  },
  {
    "name": "Štarnov",
    "lat": "49.6860",
    "lon": "17.2737"
  },
  {
    "name": "Štěpánov",
    "lat": "49.6850",
    "lon": "17.2169"
  },
  {
    "name": "Šternberk",
    "lat": "49.7307",
    "lon": "17.2988"
  },
  {
    "name": "Štáblovice",
    "lat": "49.8800",
    "lon": "17.8185"
  },
  {
    "name": "Štěpánkovice",
    "lat": "49.9579",
    "lon": "18.0388"
  },
  {
    "name": "Štítina",
    "lat": "49.9148",
    "lon": "18.0126"
  },
  {
    "name": "Štíty",
    "lat": "49.9612",
    "lon": "16.7658"
  }
]